Workbook

Sheet Assumptions
A1: Enterprise Cloud & AI Transformation
A2: Financial Strategy Proposal | Prepared for: Global Enterprise Corp
A4: Model Configuration & Architecture Parameters
A5: Financial Driver Vector | B5: Base Value Assumption | C5: Strategic Context & Accounting Treatment
A6: Platform Implementation Capital ($) | B6: 450000 | C6: Capitalized system design, architecture, and deployment services.
A7: Edge Infrastructure Hardware ($) | B7: 125000 | C7: Procurement of sensor arrays, endpoints, and physical network nodes.
A8: Initial Operational Savings ($) | B8: 260000 | C8: Targeted Year 1 gross utility, process efficiency, and labor optimization.
A9: Savings Scaling Optimization Rate | B9: 0.04 | C9: Compounding annual efficiency coefficient from automated process maturity.
A10: Sustaining Maintenance Overhead ($) | B10: 35000 | C10: Recurring service legal agreements, upgrades, and support run-rate.
A11: Corporate Discount Rate (WACC) | B11: 0.085 | C11: Corporate hurdle rate optimized for present-value cash stream factoring.
A12: Strategic Valuation Horizon (Years) | B12: 5 | C12: Active duration modeled for infrastructure run lifecycle analysis.
A15: Standard Convention Notice: Royal Blue metrics denote manual assumptions input variables. Dark black outputs signify automated formula paths.

Sheet Financial Model
A1: Projected Valuation Ledger & Cash Flow Analysis
A3: Timeline Index | B3: Year 0 (CapEx) | C3: Year 1 | D3: Year 2 | E3: Year 3 | F3: Year 4 | G3: Year 5
A4: Initial Capital Investment | B4: =-(Assumptions!$B$6+Assumptions!$B$7) | C4: 0 | D4: 0 | E4: 0 | F4: 0 | G4: 0
A5: Gross Operational Savings | B5: 0 | C5: =Assumptions!$B$8 | D5: =C5*(1+Assumptions!$B$9) | E5: =D5*(1+Assumptions!$B$9) | F5: =E5*(1+Assumptions!$B$9) | G5: =F5*(1+Assumptions!$B$9)
A6: Sustaining Support Costs | B6: 0 | C6: =-Assumptions!$B$10 | D6: =-Assumptions!$B$10 | E6: =-Assumptions!$B$10 | F6: =-Assumptions!$B$10 | G6: =-Assumptions!$B$10
A7: Net Annual Cash Flow | B7: =B4+B5+B6 | C7: =C4+C5+C6 | D7: =D4+D5+D6 | E7: =E4+E5+E6 | F7: =F4+F5+F6 | G7: =G4+G5+G6
A8: Cumulative Nominal Cash Flow | B8: =B7 | C8: =B8+C7 | D8: =C8+D7 | E8: =D8+E7 | F8: =E8+F7 | G8: =F8+G7
A9: Present Value Factor | B9: =1/(1+Assumptions!$B$11)^0 | C9: =1/(1+Assumptions!$B$11)^1 | D9: =1/(1+Assumptions!$B$11)^2 | E9: =1/(1+Assumptions!$B$11)^3 | F9: =1/(1+Assumptions!$B$11)^4 | G9: =1/(1+Assumptions!$B$11)^5
A10: Discounted Net Cash Flow (PV) | B10: =B7*B9 | C10: =C7*C9 | D10: =D7*D9 | E10: =E7*E9 | F10: =F7*F9 | G10: =G7*G9
A11: Cumulative Present Value (NPV Trend) | B11: =B10 | C11: =B11+C10 | D11: =C11+D10 | E11: =D11+E10 | F11: =E11+F10 | G11: =F11+G10
A14: Executive Investment Scorecard Metrics
A15: Net Present Value (NPV) | B15: Internal Return Multiplier (ROI) | C15: Calculated Payback Lifecycle | D15: Total Net Capital Delta
A16: =NPV(Assumptions!$B$11,C7:G7)+B7 | B16: =SUM(C7:G7)/-B7 | C16: =IFERROR(MATCH(TRUE,INDEX(B8:G8>0,0))-2+(-INDEX(B8:G8,MATCH(TRUE,INDEX(B8:G8>0,0))-1))/INDEX(B7:G7,MATCH(TRUE,INDEX(B8:G8>0,0))),"Out of Range") | D16: =SUM(C5:G5)+SUM(C6:G6)

Sheet Notes
A1: Operational Guidelines & Architectural Design Criteria
A3: 1. Interconnected Architecture: Modifications applied inside the yellow 'Assumptions' tab propagate instantly down calculation layers.
A4: 2. Capital Outlay Alignment: Baseline software platforms and ancillary node machinery components aggregate directly into Year 0 outflows.
A5: 3. Precision Payback Formula: Calculated fields use true linear index estimation points to establish target breakeven metrics cleanly.
A6: 4. Secured Document Notice: Ensure you select 'Enable Editing' in the Microsoft Excel notification ribbons to unlock full local evaluation calculations.
