Workbook

Sheet Assumptions
A1: Technology Implementation Project
A2: Prepared for: Client Name
A4: Key Assumptions
A5: Assumption | B5: Value | C5: Notes
A6: Implementation Cost ($) | B6: 250000 | C6: One-time software / implementation spend, Year 0
A7: IoT Sensor Cost ($) | B7: 75000 | C7: One-time hardware spend, Year 0
A8: Expected Annual Savings ($), Year 1 | B8: 120000 | C8: Gross run-rate savings once solution is live
A9: Annual Savings Growth Rate | B9: 0.03 | C9: Applied year-over-year to savings (e.g. efficiency gains)
A10: Annual Maintenance / Support Cost ($) | B10: 15000 | C10: Recurring cost from Year 1 onward
A11: Discount Rate | B11: 0.08 | C11: Used to discount future cash flows for NPV
A12: Projection Horizon (Years) | B12: 5 | C12: Number of post-implementation years modeled
A14: Blue = hardcoded input. Black = formula. Edit only the yellow cells to run new scenarios.

Sheet Financial Model
A1: Technology Implementation Project — Financial Model
A3: Year | B3: 0 | C3: 1 | D3: 2 | E3: 3 | F3: 4 | G3: 5
A4: Initial Investment ($) | B4: =-(Assumptions!$B$6+Assumptions!$B$7) | C4: 0 | D4: 0 | E4: 0 | F4: 0 | G4: 0
A5: Annual Savings ($) | B5: 0 | C5: =Assumptions!$B$8 | D5: =C5*(1+Assumptions!$B$9) | E5: =D5*(1+Assumptions!$B$9) | F5: =E5*(1+Assumptions!$B$9) | G5: =F5*(1+Assumptions!$B$9)
A6: Maintenance / Support Cost ($) | B6: 0 | C6: =-Assumptions!$B$10 | D6: =-Assumptions!$B$10 | E6: =-Assumptions!$B$10 | F6: =-Assumptions!$B$10 | G6: =-Assumptions!$B$10
A7: Net Cash Flow ($) | B7: =B4+B5+B6 | C7: =C4+C5+C6 | D7: =D4+D5+D6 | E7: =E4+E5+E6 | F7: =F4+F5+F6 | G7: =G4+G5+G6
A8: Cumulative Cash Flow ($) | B8: =B7 | C8: =B8+C7 | D8: =C8+D7 | E8: =D8+E7 | F8: =E8+F7 | G8: =F8+G7
A9: Discount Factor | B9: =1/(1+Assumptions!$B$11)^B$3 | C9: =1/(1+Assumptions!$B$11)^C$3 | D9: =1/(1+Assumptions!$B$11)^D$3 | E9: =1/(1+Assumptions!$B$11)^E$3 | F9: =1/(1+Assumptions!$B$11)^F$3 | G9: =1/(1+Assumptions!$B$11)^G$3
A10: PV of Net Cash Flow ($) | B10: =B7*B9 | C10: =C7*C9 | D10: =D7*D9 | E10: =E7*E9 | F10: =F7*F9 | G10: =G7*G9
A11: Cumulative PV ($) | B11: =B10 | C11: =B11+C10 | D11: =C11+D10 | E11: =D11+E10 | F11: =E11+F10 | G11: =F11+G10
A14: Key Metrics
A15: Net Present Value (NPV) | B15: ROI (Total) | C15: Payback Period (Years) | D15: Total Net Savings (undiscounted)
A16: =NPV(Assumptions!$B$11,C7:G7)+B7 | B16: =SUM(C7:G7)/-B7 | C16: =IFERROR(MATCH(TRUE,INDEX(B8:G8>0,0))-2+(-INDEX(B8:G8,MATCH(TRUE,INDEX(B8:G8>0,0))-1))/INDEX(B7:G7,MATCH(TRUE,INDEX(B8:G8>0,0))),"Not within horizon") | D16: =SUM(C5:G5)+SUM(C6:G6)

Sheet Notes
A1: How this model works
A3: 1. All inputs live on the 'Assumptions' tab in yellow/blue cells — change any of them and every formula in 'Financial Model' recalculates automatically.
A4: 2. Year 0 captures the one-time Implementation Cost and IoT Sensor Cost as a negative cash outflow.
A5: 3. Annual Savings begin in Year 1 and grow each year by the Savings Growth Rate assumption to reflect efficiency gains or scaling.
A6: 4. Annual Maintenance/Support Cost is deducted every year from Year 1 onward.
A7: 5. NPV discounts each year's Net Cash Flow back to present value using the Discount Rate assumption (standard Excel NPV function).
A8: 6. ROI is calculated as total net cash generated over the horizon divided by the initial investment.
A9: 7. Payback Period identifies the year (interpolated to a fraction of a year) in which cumulative cash flow turns positive.
A10: 8. The embedded chart plots Net Cash Flow, Cumulative Cash Flow, and Cumulative PV over the projection horizon so you can visually spot the breakeven point.
